biomni/__init__.py
biomni/config.py
biomni/env_desc.py
biomni/env_desc_cm.py
biomni/llm.py
biomni/utils.py
biomni/version.py
biomni/agent/__init__.py
biomni/agent/a1.py
biomni/agent/env_collection.py
biomni/agent/function_generator.py
biomni/agent/qa_llm.py
biomni/agent/react.py
biomni/biorxiv_scripts/extract_biorxiv_tasks.py
biomni/biorxiv_scripts/generate_function.py
biomni/biorxiv_scripts/process_all_subjects.py
biomni/model/__init__.py
biomni/model/retriever.py
biomni/task/__init__.py
biomni/task/base_task.py
biomni/task/hle.py
biomni/task/lab_bench.py
biomni/tool/__init__.py
biomni/tool/biochemistry.py
biomni/tool/bioengineering.py
biomni/tool/bioimaging.py
biomni/tool/biophysics.py
biomni/tool/cancer_biology.py
biomni/tool/cell_biology.py
biomni/tool/database.py
biomni/tool/genetics.py
biomni/tool/genomics.py
biomni/tool/glycoengineering.py
biomni/tool/immunology.py
biomni/tool/literature.py
biomni/tool/microbiology.py
biomni/tool/molecular_biology.py
biomni/tool/pathology.py
biomni/tool/pharmacology.py
biomni/tool/physiology.py
biomni/tool/support_tools.py
biomni/tool/synthetic_biology.py
biomni/tool/systems_biology.py
biomni/tool/tool_registry.py
biomni/tool/example_mcp_tools/pubmed_mcp.py
biomni/tool/schema_db/cbioportal.pkl
biomni/tool/schema_db/clinvar.pkl
biomni/tool/schema_db/dbsnp.pkl
biomni/tool/schema_db/emdb.pkl
biomni/tool/schema_db/ensembl.pkl
biomni/tool/schema_db/geo.pkl
biomni/tool/schema_db/gnomad.pkl
biomni/tool/schema_db/gtopdb.pkl
biomni/tool/schema_db/gwas_catalog.pkl
biomni/tool/schema_db/interpro.pkl
biomni/tool/schema_db/iucn.pkl
biomni/tool/schema_db/jaspar.pkl
biomni/tool/schema_db/kegg.pkl
biomni/tool/schema_db/monarch.pkl
biomni/tool/schema_db/mpd.pkl
biomni/tool/schema_db/openfda.pkl
biomni/tool/schema_db/opentarget.pkl
biomni/tool/schema_db/paleobiology.pkl
biomni/tool/schema_db/pdb.pkl
biomni/tool/schema_db/pride.pkl
biomni/tool/schema_db/reactome.pkl
biomni/tool/schema_db/remap.pkl
biomni/tool/schema_db/stringdb.pkl
biomni-0.0.7.dist-info/licenses/LICENSE
biomni-0.0.7.dist-info/METADATA
biomni-0.0.7.dist-info/WHEEL
biomni-0.0.7.dist-info/top_level.txt
biomni-0.0.7.dist-info/RECORD
