Metadata-Version: 2.4
Name: biomni
Version: 0.0.7
Summary: Biomni
Author-email: Biomni Team <kexinh@cs.stanford.edu>
License:                                  Apache License
Project-URL: Homepage, https://github.com/snap-stanford/biomni
Project-URL: Repository, https://github.com/snap-stanford/biomni
Requires-Python: >=3.11
License-File: LICENSE
Requires-Dist: pydantic
Requires-Dist: langchain
Requires-Dist: python-dotenv
Dynamic: license-file
